README.md
setup.py
tensorsketch/__init__.py
tensorsketch/utils.py
tensorsketch.egg-info/PKG-INFO
tensorsketch.egg-info/SOURCES.txt
tensorsketch.egg-info/dependency_links.txt
tensorsketch.egg-info/requires.txt
tensorsketch.egg-info/top_level.txt
tensorsketch/modules/__init__.py
tensorsketch/modules/activation.py
tensorsketch/modules/affine.py
tensorsketch/modules/base.py
tensorsketch/modules/shape.py
tensorsketch/normalization/__init__.py
tensorsketch/normalization/base.py
tensorsketch/normalization/batch_normalization.py
tensorsketch/normalization/running_normalization.py
tensorsketch/normalization/spectral_normalization.py
tensorsketch/normalization/weight_normalization.py