Metadata-Version: 1.0
Name: tensorsketch
Version: 0.1.0
Summary: Lightweight deep learning library for TensorFlow 2.0
Home-page: http://www.github.com/RuiShu/tensorsketch
Author: Rui Shu
Author-email: ruishu@stanford.edu
License: MIT
Platform: UNKNOWN
